iot_facerecognition_client
