Metadata-Version: 1.0
Name: iot-facerecognition-client
Version: 1.1.2
Summary: python client for iot-facerecognition-server
Home-page: https://github.com/fuzun/iot-facerecognition
Author: fuzun
Author-email: fuzun54@outlook.com
License: GPLv3
Platform: UNKNOWN
